modelbit/__init__.py
modelbit/collect_dependencies.py
modelbit/environment.py
modelbit/error.py
modelbit/file_logging.py
modelbit/helpers.py
modelbit/jobs.py
modelbit/keras_wrapper.py
modelbit/model_wrappers.py
modelbit/py.typed
modelbit/runtime.py
modelbit/setup_manager.py
modelbit/snowpark.py
modelbit/source_generation.py
modelbit/telemetry.py
modelbit/utils.py
modelbit/ux.py
modelbit/api/__init__.py
modelbit/api/api.py
modelbit/api/branch_api.py
modelbit/api/clone_api.py
modelbit/api/common.py
modelbit/api/common_files_api.py
modelbit/api/dataset_api.py
modelbit/api/inference_api.py
modelbit/api/job_api.py
modelbit/api/keep_warm_api.py
modelbit/api/metadata_api.py
modelbit/api/object_api.py
modelbit/api/package_api.py
modelbit/api/registry_api.py
modelbit/api/runtime_api.py
modelbit/api/secret_api.py
modelbit/api/snowpark_api.py
modelbit/api/warehouse_api.py
modelbit/cli/__init__.py
modelbit/cli/cmdline.py
modelbit/cli/deployment_create.py
modelbit/cli/describe.py
modelbit/cli/filter.py
modelbit/cli/ui.py
modelbit/git/__init__.py
modelbit/git/clone.py
modelbit/git/common_files.py
modelbit/git/filter.py
modelbit/git/filter_process.py
modelbit/git/git_protocol.py
modelbit/git/repo_helpers.py
modelbit/git/ssh_keys.py
modelbit/git/validations.py
modelbit/git/workspace.py
modelbit/internal/__init__.py
modelbit/internal/auth.py
modelbit/internal/branch.py
modelbit/internal/cache.py
modelbit/internal/common_files.py
modelbit/internal/datasets.py
modelbit/internal/debug.py
modelbit/internal/deployments.py
modelbit/internal/describe.py
modelbit/internal/encryption.py
modelbit/internal/feature_store.py
modelbit/internal/file_stubs.py
modelbit/internal/keep_warm.py
modelbit/internal/local_config.py
modelbit/internal/metadata.py
modelbit/internal/named_lock.py
modelbit/internal/package.py
modelbit/internal/registry.py
modelbit/internal/retry.py
modelbit/internal/runtime_objects.py
modelbit/internal/runtime_slots.py
modelbit/internal/s3.py
modelbit/internal/s3_stream.py
modelbit-0.44.3.dist-info/licenses/LICENSE
modelbit-0.44.3.dist-info/METADATA
modelbit-0.44.3.dist-info/WHEEL
modelbit-0.44.3.dist-info/entry_points.txt
modelbit-0.44.3.dist-info/top_level.txt
modelbit-0.44.3.dist-info/RECORD
